mach_nix/VERSION
mach_nix/__init__.py
mach_nix/cache.py
mach_nix/deptree.py
mach_nix/ensure_nix.py
mach_nix/generate.py
mach_nix/provider_defaults.toml
mach_nix/requirements.py
mach_nix/run.py
mach_nix/versions.py
mach_nix/data/__init__.py
mach_nix/data/bucket_dict.py
mach_nix/data/nixpkgs.py
mach_nix/data/providers.py
mach_nix/generators/__init__.py
mach_nix/generators/overides_generator.py
mach_nix/nix/NIXPKGS_COMMIT
mach_nix/nix/NIXPKGS_SHA256
mach_nix/nix/PYPI_DEPS_DB_COMMIT
mach_nix/nix/PYPI_DEPS_DB_SHA256
mach_nix/nix/__init__.py
mach_nix/nix/auto_patchelf_hook.nix
mach_nix/nix/call_mach.nix
mach_nix/nix/deps-db-and-fetcher.nix
mach_nix/nix/mach.nix
mach_nix/nix/nixpkgs-json.nix
mach_nix/nix/nixpkgs-src.nix
mach_nix/nix/patchelf.sh
mach_nix/nix/python-deps.nix
mach_nix/nix/python.nix
mach_nix/resolver/__init__.py
mach_nix/resolver/resolvelib_resolver.py
mach_nix-2.4.1.dist-info/LICENSE
mach_nix-2.4.1.dist-info/METADATA
mach_nix-2.4.1.dist-info/WHEEL
mach_nix-2.4.1.dist-info/entry_points.txt
mach_nix-2.4.1.dist-info/top_level.txt
mach_nix-2.4.1.dist-info/RECORD
